Metadata-Version: 2.1
Name: aries-lib
Version: 5.4.0
Summary: Biblioteca contendo sistemas importantes pra desenvolvimento
Author: Luan Souza
Author-email: piitszkdev@outlook.com
License: MIT License
Keywords: mercado pago,mercado,banco,sql,mysql,banco de dados,python,bot,discord,connection
License-File: LICENSE
